crunchyrollsubdownloader/__init__.py
crunchyrollsubdownloader/crdl.py
crunchyrollsubdownloader-2.0.0.dist-info/COPYING
crunchyrollsubdownloader-2.0.0.dist-info/METADATA
crunchyrollsubdownloader-2.0.0.dist-info/WHEEL
crunchyrollsubdownloader-2.0.0.dist-info/entry_points.txt
crunchyrollsubdownloader-2.0.0.dist-info/top_level.txt
crunchyrollsubdownloader-2.0.0.dist-info/RECORD
