Metadata-Version: 2.1
Name: crunchyrollsubdownloader
Version: 2.0.0
Summary: This tool helps you download all of a season subtitles list, in your choosen language.
Home-page: https://github.com/ThibaultNocchi/crunchyrollsubdownloader
Author: Thibaut Nocchi
Author-email: 1619359+ThibaultNocchi@users.noreply.github.com
License: : OSI Approved :: GNU General Public License v3 (GPLv3)
Platform: UNKNOWN
Requires-Python: >=3.6
License-File: COPYING
Requires-Dist: bs4
Requires-Dist: requests
Requires-Dist: youtube-dl
Requires-Dist: lxml
